tbpaste.py
tbpaste-0.2.1.data/scripts/tbpaste
tbpaste-0.2.1.dist-info/DESCRIPTION.rst
tbpaste-0.2.1.dist-info/entry_points.txt
tbpaste-0.2.1.dist-info/METADATA
tbpaste-0.2.1.dist-info/pydist.json
tbpaste-0.2.1.dist-info/RECORD
tbpaste-0.2.1.dist-info/top_level.txt
tbpaste-0.2.1.dist-info/WHEEL
