Metadata-Version: 2.0
Name: tbpaste
Version: 0.2.1
Summary: Sentiment analysis, as easy as copy-and-paste
Home-page: https://github.com/sloria/tbpaste
Author: Steven Loria
Author-email: sloria1@gmail.com
License: MIT
Platform: UNKNOWN
Classifier: Development Status :: 3 - Alpha
Classifier: Intended Audience :: Developers
Classifier: License :: OSI Approved :: MIT License
Classifier: Natural Language :: English
Classifier: Programming Language :: Python :: 2.7
Classifier: Programming Language :: Python :: 3.3
Classifier: Programming Language :: Python :: Implementation :: CPython
Classifier: Programming Language :: Python :: Implementation :: PyPy
Requires-Dist: docopt
Requires-Dist: clint
Requires-Dist: textblob (>=0.8.2)
Requires-Dist: xerox
